{
  "openapi": "3.1.0",
  "jsonSchemaDialect": "https://json-schema.org/draft/2020-12/schema",
  "info": {
    "title": "Companion Context Protocol Care Network Lookup HTTP Adapter",
    "version": "0.1.0-draft",
    "summary": "Illustrative OpenAPI surface for CCP Care Network Lookup.",
    "description": "This OpenAPI document is an adapter sketch. JSON Schema remains the canonical CCP contract. HTTP implementations are CCP-compatible only when they preserve the same authorization, minimization, provenance, visibility, actor-boundary, contact-boundary, action-authority, revocation, and omission semantics defined by SPEC.md.",
    "license": {
      "name": "Apache-2.0",
      "url": "https://www.apache.org/licenses/LICENSE-2.0.html"
    },
    "contact": {
      "name": "Companion Context Protocol maintainers; see MAINTAINERS.md until a public source URL is assigned"
    }
  },
  "servers": [
    {
      "url": "https://example.com/ccp/v0",
      "description": "Illustrative server URL. Implementations should publish their own base URL."
    }
  ],
  "tags": [
    {
      "name": "Care Network Lookup",
      "description": "Purpose-bound lookup for one pet and one subject actor."
    }
  ],
  "paths": {
    "/care-network-lookup": {
      "post": {
        "tags": [
          "Care Network Lookup"
        ],
        "operationId": "requestCareNetworkLookup",
        "summary": "Look up one actor in a pet's care network",
        "description": "Evaluates requester identity, pet identity, subject actor identity, requested scopes, declared purpose, active grant, visibility classes, contact permissions, action authority, revocation status, and freshness. Protocol-level denials return a CCP response envelope with `status: denied`; malformed requests and transport authentication failures use ordinary HTTP errors.",
        "security": [
          {
            "bearerAuth": []
          }
        ],
        "parameters": [
          {
            "$ref": "#/components/parameters/CCPVersion"
          },
          {
            "$ref": "#/components/parameters/CCPProfile"
          },
          {
            "$ref": "#/components/parameters/RequestId"
          }
        ],
        "requestBody": {
          "required": true,
          "content": {
            "application/json": {
              "schema": {
                "$ref": "../schemas/ccp-core.schema.json#/$defs/CareNetworkLookupRequest"
              },
              "examples": {
                "care_network_lookup_request": {
                  "summary": "Care Network lookup request",
                  "externalValue": "../examples/care-network-lookup-request.json"
                }
              }
            }
          }
        },
        "responses": {
          "200": {
            "description": "CCP authorization result. The body may be `ok`, `partial`, or `denied` according to the canonical Care Network lookup response schema.",
            "content": {
              "application/json": {
                "schema": {
                  "$ref": "../schemas/ccp-core.schema.json#/$defs/CareNetworkLookupResponse"
                },
                "examples": {
                  "ok_response": {
                    "summary": "Care Network lookup response",
                    "externalValue": "../examples/care-network-lookup-response.json"
                  },
                  "contact_withheld_partial_response": {
                    "summary": "Partial response with contact channel withheld",
                    "externalValue": "../examples/care-network-lookup-contact-withheld-response.json"
                  },
                  "denied_response": {
                    "summary": "Denied Care Network lookup response",
                    "externalValue": "../examples/care-network-lookup-denied-response.json"
                  }
                }
              }
            }
          },
          "400": {
            "$ref": "#/components/responses/BadRequest"
          },
          "401": {
            "$ref": "#/components/responses/Unauthorized"
          },
          "415": {
            "$ref": "#/components/responses/UnsupportedMediaType"
          },
          "429": {
            "$ref": "#/components/responses/RateLimited"
          },
          "500": {
            "$ref": "#/components/responses/InternalServerError"
          },
          "502": {
            "$ref": "#/components/responses/BadGateway"
          },
          "503": {
            "$ref": "#/components/responses/ServiceUnavailable"
          }
        },
        "x-ccp-profile": "care-network-lookup",
        "x-ccp-version": "0.1.0-draft",
        "x-ccp-required-scope": "pet.care_network.actor_refs.read",
        "x-ccp-canonical-request-schema": "../schemas/care-network-lookup-request.schema.json",
        "x-ccp-canonical-response-schema": "../schemas/care-network-lookup-response.schema.json"
      }
    }
  },
  "components": {
    "securitySchemes": {
      "bearerAuth": {
        "type": "http",
        "scheme": "bearer",
        "description": "Illustrative transport authentication. CCP does not define an authentication mechanism."
      }
    },
    "parameters": {
      "CCPVersion": {
        "name": "CCP-Version",
        "in": "header",
        "required": false,
        "description": "Requested CCP draft version. Implementations should document supported versions.",
        "schema": {
          "type": "string",
          "example": "0.1.0-draft"
        }
      },
      "CCPProfile": {
        "name": "CCP-Profile",
        "in": "header",
        "required": false,
        "description": "Requested CCP profile.",
        "schema": {
          "type": "string",
          "enum": [
            "care-network-lookup"
          ]
        }
      },
      "RequestId": {
        "name": "X-Request-Id",
        "in": "header",
        "required": false,
        "description": "Transport-level request correlation identifier.",
        "schema": {
          "type": "string"
        }
      }
    },
    "responses": {
      "BadRequest": {
        "description": "Malformed HTTP request or request body that cannot be parsed or validated."
      },
      "Unauthorized": {
        "description": "Missing or invalid transport authentication."
      },
      "UnsupportedMediaType": {
        "description": "Request media type is not supported. Use `application/json`."
      },
      "RateLimited": {
        "description": "Request was rate limited by the HTTP implementation."
      },
      "InternalServerError": {
        "description": "Unexpected implementation error. The response is transport-level and does not replace CCP authorization decisions."
      },
      "BadGateway": {
        "description": "Upstream dependency failed."
      },
      "ServiceUnavailable": {
        "description": "Service is temporarily unavailable."
      }
    }
  }
}
